breeze/__init__.py
breeze/plugins/__init__.py
breeze/plugins/base.py
breeze/plugins/blog.py
breeze/plugins/files.py
breeze/plugins/parsing.py
breeze/plugins/templates.py
tests/__init__.py
tests/test_base.py
tests/test_blog.py
tests/test_files.py
tests/test_main.py
tests/test_parsing.py
tests/test_templates.py
libbreeze-0.5.1b0.dist-info/METADATA
libbreeze-0.5.1b0.dist-info/WHEEL
libbreeze-0.5.1b0.dist-info/top_level.txt
libbreeze-0.5.1b0.dist-info/RECORD
