Metadata-Version: 2.1
Name: libbreeze
Version: 0.5.1b0
Summary: Assemble static sites
Home-page: https://github.com/BasementCat/breeze
Author: Alec Elton
Author-email: alec.elton@gmail.com
Requires-Dist: PyYAML
Requires-Dist: jinja2
Requires-Dist: markdown
Requires-Dist: arrow
Requires-Dist: libsass
Requires-Dist: cchardet
Requires-Dist: python-magic
